{"cameraMode":{"drawMode":0,"name":"Shaded","section":"Shading Mode"},"sceneLighting":true,"audioPlay":false,"sceneViewState":{"m_AlwaysRefresh":false,"showFog":true,"showSkybox":true,"showFlares":true,"showImageEffects":true,"showParticleSystems":true,"showVisualEffectGraphs":true,"m_FxEnabled":true},"in2DMode":false,"pivot":{"x":3.607940673828125,"y":-24.219934463500978,"z":-22.706764221191408},"rotation":{"x":-0.2176813781261444,"y":-0.6271445155143738,"z":0.1887292116880417,"w":-0.7237932085990906},"size":35.185211181640628,"orthographic":false}